MANIFEST.in
README.rst
setup.py
dash/__init__.py
dash/__main__.py
dash/api.py
dash/argparser.py
dash/caller.py
dash/cli.py
dash/deployments.py
dash/environments.py
dash/git_fetches.py
dash/json_serializer.py
dash/snapshots.py
dash/stacks.py
dash/utils.py
dash_cli.egg-info/PKG-INFO
dash_cli.egg-info/SOURCES.txt
dash_cli.egg-info/dependency_links.txt
dash_cli.egg-info/entry_points.txt
dash_cli.egg-info/top_level.txt