Metadata-Version: 1.2
Name: dash-cli
Version: 0.1.4
Summary: Python command line interface to CWP's Dash API.
Home-page: https://github.com/thepearson/cwp-cli
Author: Craig Pearson
Author-email: thepearson@gmail.com
License: UNKNOWN
Platform: UNKNOWN
Requires-Python: >=2.7
